{
  "version": 1,
  "date": "2026-07-06",
  "week": "2026-W28",
  "resetCounter": 5,
  "activeIssueNumber": 6,
  "activeIssueUrl": "https://github.com/the-sudipta/the-sudipta/issues/6",
  "layout": {
    "size": 4,
    "mission": "Stabilize the Security Core",
    "wumpus": "A4",
    "pits": [
      "A1",
      "D3"
    ],
    "bats": [
      "C3"
    ],
    "artifacts": {
      "A2": "Algorithm Relic",
      "C1": "Security Key",
      "B3": "Blockchain Ledger",
      "C2": "Bioinformatics Sample",
      "A3": "Quantum Fragment"
    }
  },
  "player": {
    "room": "B2",
    "arrows": 2,
    "status": "exploring",
    "score": 0,
    "artifacts": 0,
    "moves": 0
  },
  "revealed": [
    "B2"
  ],
  "collected": [],
  "history": [
    {
      "actor": "the-sudipta",
      "command": "/render",
      "message": "Rendered the current cave state.",
      "at": "2026-07-05T19:38:21.141Z"
    },
    {
      "actor": "github",
      "command": "/weekly-reset",
      "message": "A new weekly cave has opened for 2026-W28.",
      "at": "2026-07-05T19:38:21.141Z"
    },
    {
      "actor": "the-sudipta",
      "command": "/render",
      "message": "Rendered the current cave state.",
      "at": "2026-06-28T19:41:44.500Z"
    },
    {
      "actor": "github",
      "command": "/weekly-reset",
      "message": "A new weekly cave has opened for 2026-W27.",
      "at": "2026-06-28T19:41:44.500Z"
    },
    {
      "actor": "the-sudipta",
      "command": "/render",
      "message": "Rendered the current cave state.",
      "at": "2026-06-21T19:56:55.037Z"
    },
    {
      "actor": "github",
      "command": "/weekly-reset",
      "message": "A new weekly cave has opened for 2026-W26.",
      "at": "2026-06-21T19:56:55.037Z"
    },
    {
      "actor": "the-sudipta",
      "command": "/render",
      "message": "Rendered the current cave state.",
      "at": "2026-06-14T19:50:28.905Z"
    },
    {
      "actor": "github",
      "command": "/weekly-reset",
      "message": "A new weekly cave has opened for 2026-W25.",
      "at": "2026-06-14T19:50:28.905Z"
    }
  ],
  "latest": {
    "actor": "the-sudipta",
    "command": "/render",
    "message": "Rendered the current cave state."
  },
  "dailyLeaderboard": {},
  "weeklyLeaderboard": {},
  "allTimeLeaderboard": {
    "the-sudipta": 3
  },
  "allTime": {
    "huntsWon": 0,
    "artifacts": 0,
    "moves": 1
  }
}
